Metadata-Version: 1.0
Name: num-calculus
Version: 0.1
Summary: numerical first derivative
Home-page: http://github.com/niamenen/num_calculus
Author: Arttu Nieminen
Author-email: arttu.nieminen@tuni.fi
License: -
Platform: UNKNOWN
